dateiendifferenz/README.MD
dateiendifferenz/__init__.py
dateiendifferenz/requirements.txt
dateiendifferenz/stringsext.exe
dateiendifferenz/thirdparty.json
dateiendifferenz-0.12.dist-info/LICENSE.rst
dateiendifferenz-0.12.dist-info/METADATA
dateiendifferenz-0.12.dist-info/WHEEL
dateiendifferenz-0.12.dist-info/top_level.txt
dateiendifferenz-0.12.dist-info/RECORD
