Metadata-Version: 2.1
Name: dateiendifferenz
Version: 0.12
Summary: tailored for handling file parsing and encoding conversion
Home-page: https://github.com/hansalemaos/dateiendifferenz
Author: Johannes Fischer
Author-email: aulasparticularesdealemaosp@gmail.com
License: MIT
Keywords: parsing,lowlevel
Classifier: Development Status :: 4 - Beta
Classifier: Programming Language :: Python :: 3 :: Only
Classifier: Programming Language :: Python :: 3.10
Classifier: Topic :: Software Development :: Libraries :: Python Modules
Classifier: Topic :: Utilities
License-File: LICENSE.rst
Requires-Dist: numpy
Requires-Dist: pandas
Requires-Dist: subprocess-alive
Requires-Dist: touchtouch
